{"cameraMode":{"drawMode":0,"name":"Shaded","section":"Shading Mode"},"sceneLighting":true,"audioPlay":false,"sceneViewState":{"m_AlwaysRefresh":false,"showFog":true,"showSkybox":true,"showFlares":true,"showImageEffects":true,"showParticleSystems":true,"showVisualEffectGraphs":true,"m_FxEnabled":true},"in2DMode":false,"pivot":{"x":-0.8591168522834778,"y":0.5135135054588318,"z":0.14881852269172669},"rotation":{"x":-0.042807284742593768,"y":0.8274533152580261,"z":-0.06368369609117508,"w":-0.5562852621078491},"size":5.204267501831055,"orthographic":false}